adversarial_workflow/__init__.py
adversarial_workflow/__main__.py
adversarial_workflow/cli.py
adversarial_workflow/evaluators/__init__.py
adversarial_workflow/evaluators/builtins.py
adversarial_workflow/evaluators/config.py
adversarial_workflow/evaluators/discovery.py
adversarial_workflow/evaluators/runner.py
adversarial_workflow/templates/.aider.conf.yml.template
adversarial_workflow/templates/.env.example.template
adversarial_workflow/templates/README.template
adversarial_workflow/templates/config.yml.template
adversarial_workflow/templates/evaluate_plan.sh.template
adversarial_workflow/templates/example-task.md.template
adversarial_workflow/templates/proofread_content.sh.template
adversarial_workflow/templates/review_implementation.sh.template
adversarial_workflow/templates/validate_tests.sh.template
adversarial_workflow/templates/agent-context/AGENT-SYSTEM-GUIDE.md
adversarial_workflow/templates/agent-context/README.md.template
adversarial_workflow/templates/agent-context/agent-handoffs-minimal.json.template
adversarial_workflow/templates/agent-context/agent-handoffs.json.template
adversarial_workflow/templates/agent-context/current-state.json.template
adversarial_workflow/utils/__init__.py
adversarial_workflow/utils/citations.py
adversarial_workflow/utils/colors.py
adversarial_workflow/utils/config.py
adversarial_workflow/utils/file_splitter.py
adversarial_workflow/utils/validation.py
adversarial_workflow-0.7.0.dist-info/licenses/LICENSE
adversarial_workflow-0.7.0.dist-info/METADATA
adversarial_workflow-0.7.0.dist-info/WHEEL
adversarial_workflow-0.7.0.dist-info/entry_points.txt
adversarial_workflow-0.7.0.dist-info/top_level.txt
adversarial_workflow-0.7.0.dist-info/RECORD
