Metadata-Version: 2.4
Name: adversarial-workflow
Version: 0.7.0
Summary: Multi-stage AI evaluation system for task plans, code review, and test validation
Author: Fredrik Matheson
License: MIT
Project-URL: Homepage, https://github.com/movito/adversarial-workflow
Project-URL: Documentation, https://github.com/movito/adversarial-workflow/blob/main/README.md
Project-URL: Repository, https://github.com/movito/adversarial-workflow
Project-URL: Issues, https://github.com/movito/adversarial-workflow/issues
Keywords: code-review,ai,llm,quality,testing,aider
Classifier: Development Status :: 4 - Beta
Classifier: Intended Audience :: Developers
Classifier: License :: OSI Approved :: MIT License
Classifier: Programming Language :: Python :: 3
Classifier: Programming Language :: Python :: 3.10
Classifier: Programming Language :: Python :: 3.11
Classifier: Programming Language :: Python :: 3.12
Classifier: Topic :: Software Development :: Quality Assurance
Classifier: Topic :: Software Development :: Testing
Requires-Python: >=3.10
License-File: LICENSE
Requires-Dist: pyyaml>=6.0
Requires-Dist: python-dotenv>=0.19.0
Requires-Dist: aider-chat>=0.86.0
Requires-Dist: aiohttp>=3.8.0
Provides-Extra: dev
Requires-Dist: pytest>=7.0; extra == "dev"
Requires-Dist: pytest-cov>=3.0; extra == "dev"
Requires-Dist: pytest-asyncio>=0.21.0; extra == "dev"
Requires-Dist: black>=22.0; extra == "dev"
Requires-Dist: isort>=5.0; extra == "dev"
Requires-Dist: flake8>=4.0; extra == "dev"
Requires-Dist: tomli>=2.0; python_version < "3.11" and extra == "dev"
Dynamic: license-file
